common/__init__.py
common/decorators.py
common/descriptors.py
common/metaclasses.py
common/utils.py
server_module/__init__.py
server_module/server_database.py
server_module/server_gui.py
mess_chat_123_server-0.0.1.dist-info/METADATA
mess_chat_123_server-0.0.1.dist-info/WHEEL
mess_chat_123_server-0.0.1.dist-info/top_level.txt
mess_chat_123_server-0.0.1.dist-info/RECORD
